cloud_pipelines/__init__.py
cloud_pipelines/_components/components/__init__.py
cloud_pipelines/_components/components/_airflow_op.py
cloud_pipelines/_components/components/_component_store.py
cloud_pipelines/_components/components/_components.py
cloud_pipelines/_components/components/_data_passing.py
cloud_pipelines/_components/components/_dynamic.py
cloud_pipelines/_components/components/_key_value_store.py
cloud_pipelines/_components/components/_naming.py
cloud_pipelines/_components/components/_python_op.py
cloud_pipelines/_components/components/_python_to_graph_component.py
cloud_pipelines/_components/components/_structures.py
cloud_pipelines/_components/components/_yaml_utils.py
cloud_pipelines/_components/components/modelbase.py
cloud_pipelines/_components/components/structures/__init__.py
cloud_pipelines/components/__init__.py
cloud_pipelines/components/_lightweight.py
cloud_pipelines/components/_serialization.py
cloud_pipelines/components/_serializers.py
cloud_pipelines/components/_serializers_ml.py
cloud_pipelines/components/structures/__init__.py
cloud_pipelines/orchestration/__init__.py
cloud_pipelines/orchestration/runners.py
cloud_pipelines/orchestration/launchers/__init__.py
cloud_pipelines/orchestration/launchers/_container_utils.py
cloud_pipelines/orchestration/launchers/google_cloud_batch_launcher.py
cloud_pipelines/orchestration/launchers/google_cloud_vertex_custom_job_launcher.py
cloud_pipelines/orchestration/launchers/interfaces.py
cloud_pipelines/orchestration/launchers/kubernetes_utils.py
cloud_pipelines/orchestration/launchers/local_docker_launcher.py
cloud_pipelines/orchestration/launchers/local_environment_launcher.py
cloud_pipelines/orchestration/launchers/local_kubernetes_launcher.py
cloud_pipelines/orchestration/launchers/naming_utils.py
cloud_pipelines/orchestration/storage_providers/__init__.py
cloud_pipelines/orchestration/storage_providers/google_cloud_storage.py
cloud_pipelines/orchestration/storage_providers/interfaces.py
cloud_pipelines-0.25.9.23.dist-info/licenses/LICENSE
cloud_pipelines-0.25.9.23.dist-info/METADATA
cloud_pipelines-0.25.9.23.dist-info/WHEEL
cloud_pipelines-0.25.9.23.dist-info/top_level.txt
cloud_pipelines-0.25.9.23.dist-info/RECORD
