Metadata-Version: 2.4
Name: cloud-pipelines
Version: 0.25.9.23
Summary: SDK for Cloud Pipelines
Author-email: Alexey Volkov <alexey.volkov@ark-kun.com>
License: Apache License 2.0
Project-URL: homepage, https://cloud-pipelines.net
Project-URL: source, https://github.com/Cloud-Pipelines/sdk
Project-URL: issues, https://github.com/Cloud-Pipelines/sdk/issues
Classifier: Development Status :: 4 - Beta
Classifier: Intended Audience :: Developers
Classifier: Intended Audience :: Education
Classifier: Intended Audience :: Science/Research
Classifier: License :: OSI Approved :: Apache Software License
Classifier: Operating System :: OS Independent
Classifier: Programming Language :: Python :: 3
Classifier: Programming Language :: Python :: 3.7
Classifier: Programming Language :: Python :: 3.8
Classifier: Programming Language :: Python :: 3.9
Classifier: Programming Language :: Python :: 3.10
Classifier: Programming Language :: Python :: 3.11
Classifier: Programming Language :: Python :: 3.12
Classifier: Programming Language :: Python :: 3.13
Classifier: Topic :: Scientific/Engineering
Classifier: Topic :: Scientific/Engineering :: Artificial Intelligence
Requires-Python: >=3.7
License-File: LICENSE
Requires-Dist: PyYAML
Requires-Dist: docker<7.0.0,>=4.4.0
Requires-Dist: docstring-parser>=0.16
Requires-Dist: isodate~=0.6.1
Requires-Dist: requests
Requires-Dist: strip-hints>=0.1.8
Provides-Extra: tests
Requires-Dist: mock; extra == "tests"
Dynamic: license-file
